persishell/__init__.py
persishell/shell.py
persishell-0.1.1.dist-info/LICENSE
persishell-0.1.1.dist-info/METADATA
persishell-0.1.1.dist-info/WHEEL
persishell-0.1.1.dist-info/top_level.txt
persishell-0.1.1.dist-info/RECORD
