Metadata-Version: 2.1
Name: persishell
Version: 0.1.1
Summary: A simple wrapper around subprocess with persistent environment variables
Author-email: Jiakun Yan <jiakunyan1998@gmail.com>
License: MIT License
Requires-Python: >=3.7
License-File: LICENSE
